dsv_cli-0.0.1.data/scripts/dsv
lib/dsv/__init__.py
lib/dsv/__main__.py
lib/dsv/dsv.py
dsv_cli-0.0.1.dist-info/LICENSE
dsv_cli-0.0.1.dist-info/METADATA
dsv_cli-0.0.1.dist-info/WHEEL
dsv_cli-0.0.1.dist-info/top_level.txt
dsv_cli-0.0.1.dist-info/RECORD
