Metadata-Version: 2.1
Name: dsv-cli
Version: 0.0.1
Summary: Versioning for Data Science
Home-page: https://github.com/AlbertoCastelo/DSV
Author: Alberto Castelo
Author-email: alberto.castelo.becerra@gmail.com
License: UNKNOWN
Platform: UNKNOWN
Classifier: Programming Language :: Python :: 3
Classifier: License :: OSI Approved :: MIT License
Classifier: Operating System :: OS Independent
Requires-Python: >=3.7
